{
    "success": true,
    "error": null,
    "body": {
        "questions": [
            {
             
              "data": {
                    "answers": [
                        {
                            "id": 0,
                            "text": "ب",
                            "group": "a",
                            "sound": ""
                        },
                        {
                            "id": 0,
                            "text": "",
                            "group": "b",
                            "sound": "https://s3.eu-central-1.amazonaws.com/arabee/uploads/A0/sounds/mp3/e52a589c86d56c5feb13ae541a297387.mp3"
                        },
                        {
                            "id": 1,
                            "text": "ت",
                            "group": "a",
                            "sound": ""
                        },
                        {
                            "id": 1,
                            "text": "",
                            "group": "b",
                            "sound": "https://s3.eu-central-1.amazonaws.com/arabee/uploads/A0/sounds/mp3/d40f84cb4141da6a7d4cf4f8e0a94d95.mp3"
                        },
                        {
                            "id": 2,
                            "text": "ث",
                            "group": "a",
                            "sound": ""
                        },
                        {
                            "id": 2,
                            "text": "",
                            "group": "b",
                            "sound": "https://s3.eu-central-1.amazonaws.com/arabee/uploads/A0/sounds/mp3/187b671b8293f683517e6d3a069de2b4.mp3"
                        }
                        
                    ],
                    "question": {
                        "questionText": "Drag the letter to its sound"
                    }
                },
                "order": 11,
                "questionId": 150869,
                "templateId": 6
            }
        ],
        "onesignalData": {
            "data1": "ب",
            "data2": "letter"
        }
    }
}